sd_jwt/__init__.py
sd_jwt/bin/__init__.py
sd_jwt/bin/demo.py
sd_jwt/bin/generate.py
sd_jwt/common.py
sd_jwt/disclosure.py
sd_jwt/holder.py
sd_jwt/issuer.py
sd_jwt/utils/__init__.py
sd_jwt/utils/demo_settings.yml
sd_jwt/utils/demo_utils.py
sd_jwt/utils/formatting.py
sd_jwt/utils/yaml_specification.py
sd_jwt/verifier.py
sd_jwt-0.10.4.dist-info/LICENSE
sd_jwt-0.10.4.dist-info/METADATA
sd_jwt-0.10.4.dist-info/WHEEL
sd_jwt-0.10.4.dist-info/entry_points.txt
sd_jwt-0.10.4.dist-info/RECORD
