Metadata-Version: 2.1
Name: sd-jwt
Version: 0.10.4
Summary: The reference implementation of the IETF SD-JWT specification.
Author: Daniel Fett
Author-email: mail@danielfett.de
Requires-Python: >=3.8,<4.0
Classifier: Programming Language :: Python :: 3
Classifier: Programming Language :: Python :: 3.8
Classifier: Programming Language :: Python :: 3.9
Classifier: Programming Language :: Python :: 3.10
Classifier: Programming Language :: Python :: 3.11
Classifier: Programming Language :: Python :: 3.12
Requires-Dist: jwcrypto (>=1.3.1)
Requires-Dist: pyyaml (>=5.4)
